gopro_sync/__init__.py
gopro_sync/synchronizer.py
gopro_sync/utils/__init__.py
gopro_sync/utils/arguments.py
gopro_sync-0.0.12.dist-info/LICENSE
gopro_sync-0.0.12.dist-info/METADATA
gopro_sync-0.0.12.dist-info/WHEEL
gopro_sync-0.0.12.dist-info/entry_points.txt
gopro_sync-0.0.12.dist-info/top_level.txt
gopro_sync-0.0.12.dist-info/RECORD
