Metadata-Version: 2.1
Name: gopro-sync
Version: 0.0.12
Summary: A tool to synchronize GoPro videos
Author-email: Moris Doratiotto <me@moris.dev>
License: MIT License
Project-URL: Homepage, https://github.com/Mortafix/GoPro_Synchronize
Keywords: gopro,video,sync
Classifier: Programming Language :: Python :: 3
Classifier: License :: OSI Approved :: MIT License
Classifier: Operating System :: OS Independent
Requires-Python: >=3.8
License-File: LICENSE
Requires-Dist: colorifix (==2.0.4)
Requires-Dist: tqdm (==4.64.1)
